discord/ext/getch/__init__.py
discord/ext/getch/builder.py
discord/ext/getch/manager.py
discord/ext/getch/mixin.py
discord_ext_getch-0.1.0.dist-info/LICENSE
discord_ext_getch-0.1.0.dist-info/METADATA
discord_ext_getch-0.1.0.dist-info/WHEEL
discord_ext_getch-0.1.0.dist-info/top_level.txt
discord_ext_getch-0.1.0.dist-info/RECORD
